{
  "subtask_name": "subtask_07_Find_and_rescue_LostPersonNora_LostPersonLeo_LostPersonMaya_and_LostPersonEthan",
  "nodes": [
    {
      "id": 0,
      "action": "explore robot1 (5)",
      "action_type": "explore",
      "robot": "robot1",
      "objects": [],
      "parallel_group": 0
    },
    {
      "id": 1,
      "action": "gotoobject robot1 lostpersonethan (1)",
      "action_type": "gotoobject",
      "robot": "robot1",
      "objects": [
        "lostpersonethan"
      ],
      "parallel_group": 1
    },
    {
      "id": 2,
      "action": "carry robot1 lostpersonethan (1)",
      "action_type": "carry",
      "robot": "robot1",
      "objects": [
        "lostpersonethan"
      ],
      "parallel_group": 2
    },
    {
      "id": 3,
      "action": "gotoobject robot1 lostpersonleo (1)",
      "action_type": "gotoobject",
      "robot": "robot1",
      "objects": [
        "lostpersonleo"
      ],
      "parallel_group": 1
    },
    {
      "id": 4,
      "action": "carry robot1 lostpersonleo (1)",
      "action_type": "carry",
      "robot": "robot1",
      "objects": [
        "lostpersonleo"
      ],
      "parallel_group": 2
    },
    {
      "id": 5,
      "action": "gotoobject robot1 lostpersonmaya (1)",
      "action_type": "gotoobject",
      "robot": "robot1",
      "objects": [
        "lostpersonmaya"
      ],
      "parallel_group": 1
    },
    {
      "id": 6,
      "action": "carry robot1 lostpersonmaya (1)",
      "action_type": "carry",
      "robot": "robot1",
      "objects": [
        "lostpersonmaya"
      ],
      "parallel_group": 2
    },
    {
      "id": 7,
      "action": "gotoobject robot1 lostpersonnora (1)",
      "action_type": "gotoobject",
      "robot": "robot1",
      "objects": [
        "lostpersonnora"
      ],
      "parallel_group": 1
    },
    {
      "id": 8,
      "action": "carry robot1 lostpersonnora (1)",
      "action_type": "carry",
      "robot": "robot1",
      "objects": [
        "lostpersonnora"
      ],
      "parallel_group": 2
    },
    {
      "id": 9,
      "action": "gotoobject robot1 depositfacility (1)",
      "action_type": "gotoobject",
      "robot": "robot1",
      "objects": [
        "depositfacility"
      ],
      "parallel_group": 3
    },
    {
      "id": 10,
      "action": "dropoff robot1 lostpersonnora depositfacility (1)",
      "action_type": "dropoff",
      "robot": "robot1",
      "objects": [
        "lostpersonnora",
        "depositfacility"
      ],
      "parallel_group": 4
    },
    {
      "id": 11,
      "action": "dropoff robot1 lostpersonmaya depositfacility (1)",
      "action_type": "dropoff",
      "robot": "robot1",
      "objects": [
        "lostpersonmaya",
        "depositfacility"
      ],
      "parallel_group": 4
    },
    {
      "id": 12,
      "action": "dropoff robot1 lostpersonleo depositfacility (1)",
      "action_type": "dropoff",
      "robot": "robot1",
      "objects": [
        "lostpersonleo",
        "depositfacility"
      ],
      "parallel_group": 4
    },
    {
      "id": 13,
      "action": "dropoff robot1 lostpersonethan depositfacility (1)",
      "action_type": "dropoff",
      "robot": "robot1",
      "objects": [
        "lostpersonethan",
        "depositfacility"
      ],
      "parallel_group": 4
    }
  ],
  "edges": [
    {
      "from_id": 0,
      "to_id": 1,
      "dependency_type": "causal"
    },
    {
      "from_id": 1,
      "to_id": 2,
      "dependency_type": "causal"
    },
    {
      "from_id": 2,
      "to_id": 9,
      "dependency_type": "binding"
    },
    {
      "from_id": 9,
      "to_id": 13,
      "dependency_type": "causal"
    },
    {
      "from_id": 0,
      "to_id": 3,
      "dependency_type": "causal"
    },
    {
      "from_id": 3,
      "to_id": 4,
      "dependency_type": "causal"
    },
    {
      "from_id": 4,
      "to_id": 9,
      "dependency_type": "binding"
    },
    {
      "from_id": 9,
      "to_id": 12,
      "dependency_type": "causal"
    },
    {
      "from_id": 0,
      "to_id": 5,
      "dependency_type": "causal"
    },
    {
      "from_id": 5,
      "to_id": 6,
      "dependency_type": "causal"
    },
    {
      "from_id": 6,
      "to_id": 9,
      "dependency_type": "binding"
    },
    {
      "from_id": 9,
      "to_id": 11,
      "dependency_type": "causal"
    },
    {
      "from_id": 0,
      "to_id": 7,
      "dependency_type": "causal"
    },
    {
      "from_id": 7,
      "to_id": 8,
      "dependency_type": "causal"
    },
    {
      "from_id": 8,
      "to_id": 9,
      "dependency_type": "binding"
    },
    {
      "from_id": 9,
      "to_id": 10,
      "dependency_type": "causal"
    }
  ],
  "parallel_groups": {
    "0": [
      0
    ],
    "1": [
      1,
      3,
      5,
      7
    ],
    "2": [
      2,
      4,
      6,
      8
    ],
    "3": [
      9
    ],
    "4": [
      10,
      11,
      12,
      13
    ]
  },
  "binding_edges": [
    {
      "from": 2,
      "to": 9
    },
    {
      "from": 4,
      "to": 9
    },
    {
      "from": 6,
      "to": 9
    },
    {
      "from": 8,
      "to": 9
    }
  ]
}