{
  "task_name": "task",
  "nodes": [
    {
      "id": 1,
      "name": "subtask_01_Place_the_Bowl_in_the_Cabinet",
      "objects": [
        "robot1",
        "bowl",
        "cabinet",
        "diningtable"
      ],
      "preconds": [
        "Robot is in the kitchen.",
        "Bowl is on the dining table.",
        "Cabinet is closed.",
        "Robot is not holding the bowl."
      ],
      "effects": [
        "Bowl is placed inside the cabinet.",
        "Cabinet is closed.",
        "Robot is not holding the bowl."
      ]
    },
    {
      "id": 2,
      "name": "subtask_02_Place_the_Bread_on_the_CounterTop",
      "objects": [
        "robot1",
        "bread",
        "diningtable",
        "countertop"
      ],
      "preconds": [
        "Robot is not in action",
        "Robot is at the floor",
        "Bread is on the dining table",
        "Countertop is on the floor",
        "Robot is not holding the bread"
      ],
      "effects": [
        "Bread is on the countertop",
        "Robot is not holding the bread",
        "Robot is not in action"
      ]
    },
    {
      "id": 3,
      "name": "subtask_03_Place_the_Fork_in_a_Drawer",
      "objects": [
        "robot1",
        "fork",
        "drawer1",
        "diningtable",
        "floor",
        "kitchen"
      ],
      "preconds": [
        "Robot is in the kitchen.",
        "Fork is on the dining table.",
        "Drawer is on the floor.",
        "Robot is not holding the fork.",
        "Drawer is initially closed."
      ],
      "effects": [
        "Fork is placed in the drawer.",
        "Drawer is closed.",
        "Robot is near the drawer."
      ]
    },
    {
      "id": 4,
      "name": "subtask_04_Place_the_Pan_on_the_StoveBurner",
      "objects": [
        "robot1",
        "pan",
        "stoveburner",
        "diningtable"
      ],
      "preconds": [
        "Robot is not in action",
        "Robot is in the kitchen",
        "Pan is on the dining table",
        "Robot is not holding the pan"
      ],
      "effects": [
        "Pan is on the stoveburner",
        "Robot is not holding the pan"
      ]
    },
    {
      "id": 5,
      "name": "subtask_05_Place_the_Spoon_in_a_Drawer",
      "objects": [
        "robot1",
        "spoon",
        "drawer1",
        "diningtable",
        "floor"
      ],
      "preconds": [
        "Robot is not in action.",
        "Robot is at the kitchen.",
        "Spoon is on the dining table.",
        "Drawer is on the floor.",
        "Robot is close to the drawer.",
        "Robot is not holding the spoon."
      ],
      "effects": [
        "Spoon is placed in the drawer.",
        "Robot is close to the drawer."
      ]
    },
    {
      "id": 6,
      "name": "subtask_06_Place_the_Tomato_in_the_Fridge",
      "objects": [
        "robot1",
        "tomato",
        "fridge",
        "diningtable"
      ],
      "preconds": [
        "Robot is not in action.",
        "Robot is in the kitchen.",
        "Tomato is on the dining table.",
        "Fridge is closed."
      ],
      "effects": [
        "Tomato is placed in the fridge.",
        "Robot is not holding the tomato.",
        "Fridge is closed."
      ]
    }
  ],
  "edges": [
    {
      "from_id": 1,
      "to_id": 2,
      "dependency_type": "resource",
      "reason": "Both subtasks involve the dining table"
    },
    {
      "from_id": 1,
      "to_id": 3,
      "dependency_type": "resource",
      "reason": "Both subtasks involve the dining table"
    },
    {
      "from_id": 1,
      "to_id": 4,
      "dependency_type": "resource",
      "reason": "Both subtasks involve the dining table"
    },
    {
      "from_id": 1,
      "to_id": 5,
      "dependency_type": "resource",
      "reason": "Both subtasks involve the dining table"
    },
    {
      "from_id": 1,
      "to_id": 6,
      "dependency_type": "resource",
      "reason": "Both subtasks involve the dining table"
    },
    {
      "from_id": 2,
      "to_id": 3,
      "dependency_type": "resource",
      "reason": "Both subtasks involve the dining table"
    },
    {
      "from_id": 2,
      "to_id": 4,
      "dependency_type": "resource",
      "reason": "Both subtasks involve the dining table"
    },
    {
      "from_id": 2,
      "to_id": 5,
      "dependency_type": "resource",
      "reason": "Both subtasks involve the dining table"
    },
    {
      "from_id": 2,
      "to_id": 6,
      "dependency_type": "resource",
      "reason": "Both subtasks involve the dining table"
    },
    {
      "from_id": 3,
      "to_id": 4,
      "dependency_type": "resource",
      "reason": "Both subtasks involve the dining table"
    },
    {
      "from_id": 3,
      "to_id": 5,
      "dependency_type": "resource",
      "reason": "Both subtasks involve the drawer"
    },
    {
      "from_id": 3,
      "to_id": 6,
      "dependency_type": "resource",
      "reason": "Both subtasks involve the dining table"
    },
    {
      "from_id": 4,
      "to_id": 5,
      "dependency_type": "resource",
      "reason": "Both subtasks involve the dining table"
    },
    {
      "from_id": 4,
      "to_id": 6,
      "dependency_type": "resource",
      "reason": "Both subtasks involve the dining table"
    },
    {
      "from_id": 5,
      "to_id": 6,
      "dependency_type": "resource",
      "reason": "Both subtasks involve the dining table"
    }
  ],
  "parallel_groups": {
    "0": [
      1
    ],
    "1": [
      2
    ],
    "2": [
      3
    ],
    "3": [
      4
    ],
    "4": [
      5
    ],
    "5": [
      6
    ]
  }
}